frostfs_testlib_plugin_sbercloud/__init__.py
frostfs_testlib_plugin_sbercloud/sbercloud_auth_requests.py
frostfs_testlib_plugin_sbercloud/sbercloud_client.py
frostfs_testlib_plugin_sbercloud/sbercloud_host.py
frostfs_testlib_plugin_sbercloud-1.2.0.dist-info/LICENSE
frostfs_testlib_plugin_sbercloud-1.2.0.dist-info/METADATA
frostfs_testlib_plugin_sbercloud-1.2.0.dist-info/WHEEL
frostfs_testlib_plugin_sbercloud-1.2.0.dist-info/entry_points.txt
frostfs_testlib_plugin_sbercloud-1.2.0.dist-info/top_level.txt
frostfs_testlib_plugin_sbercloud-1.2.0.dist-info/RECORD
