Metadata-Version: 2.1
Name: frostfs-testlib-plugin-sbercloud
Version: 1.2.0
Summary: FrostFS testlib plugin providing host management functionality for cloud provider Sbercloud
Author-email: NSPCC <info@nspcc.ru>
License: GNU General Public License v3 (GPLv3)
Project-URL: Homepage, https://github.com/TrueCloudLab/frostfs-testlib-plugin-sbercloud/
Keywords: frostfs,test
Classifier: License :: OSI Approved :: GNU General Public License v3 (GPLv3)
Classifier: Programming Language :: Python
Classifier: Programming Language :: Python :: 3
Requires-Python: ==3.10.*
License-File: LICENSE
Requires-Dist: frostfs-testlib (>=1.2.0)
Requires-Dist: requests (>=2.28.0)
Provides-Extra: dev
Requires-Dist: black ; extra == 'dev'
Requires-Dist: bumpver ; extra == 'dev'
Requires-Dist: isort ; extra == 'dev'
Requires-Dist: pre-commit ; extra == 'dev'
